ebx_checklist/__init__.py
ebx_checkbox-1.0.1.dist-info/LICENSE
ebx_checkbox-1.0.1.dist-info/METADATA
ebx_checkbox-1.0.1.dist-info/WHEEL
ebx_checkbox-1.0.1.dist-info/top_level.txt
ebx_checkbox-1.0.1.dist-info/RECORD
