Metadata-Version: 2.1
Name: ebx-checkbox
Version: 1.0.1
Summary: CheckBox and OptionBox to Python
Home-page: https://github.com/faustobranco/ebx_checkbox
Author: Fausto Branco
Author-email: fausto.branco@gmail.com
License: UNKNOWN
Project-URL: Bug Tracker, https://github.com/faustobranco/ebx_checkbox/issues
Platform: UNKNOWN
Classifier: Programming Language :: Python :: 3
Classifier: License :: OSI Approved :: MIT License
Classifier: Operating System :: OS Independent
Requires-Python: >=3.6
